Metadata-Version: 1.0
Name: RNdistributions
Version: 0.1
Summary: Gaussian distributions
Home-page: UNKNOWN
Author: MH Rajon
Author-email: rajon789@gmail.com
License: UNKNOWN
Platform: UNKNOWN
